CHANGES.rst
CONTRIBUTORS.rst
MANIFEST.in
README.rst
VERSION
setup.py
docs/LICENSE.GPL
docs/LICENSE.rst
docs/index.rst
src/visaplan/__init__.py
src/visaplan.plone.base.egg-info/PKG-INFO
src/visaplan.plone.base.egg-info/SOURCES.txt
src/visaplan.plone.base.egg-info/dependency_links.txt
src/visaplan.plone.base.egg-info/entry_points.txt
src/visaplan.plone.base.egg-info/namespace_packages.txt
src/visaplan.plone.base.egg-info/not-zip-safe
src/visaplan.plone.base.egg-info/requires.txt
src/visaplan.plone.base.egg-info/top_level.txt
src/visaplan/plone/__init__.py
src/visaplan/plone/base/__init__.py
src/visaplan/plone/base/adapter.py
src/visaplan/plone/base/browserview.py
src/visaplan/plone/base/configure.zcml
src/visaplan/plone/base/exceptions.py
src/visaplan/plone/base/mixin.py
src/visaplan/plone/base/permissions.py
src/visaplan/plone/base/typestr.py