Metadata-Version: 1.1
Name: visaplan.plone.base
Version: 1.1
Summary: Base modules for UNITRACC, a Plone customization
Home-page: https://pypi.org/project/visaplan.plone.base
Author: Tobias Herp
Author-email: tobias.herp@visaplan.com
License: GPL version 2
Platform: UNKNOWN
Classifier: Environment :: Web Environment
Classifier: Framework :: Plone
Classifier: Framework :: Plone :: 4.3
Classifier: Programming Language :: Python
Classifier: Programming Language :: Python :: 2.7
Classifier: Intended Audience :: Developers
Classifier: Natural Language :: German
Classifier: Operating System :: OS Independent
Classifier: License :: OSI Approved :: GNU General Public License v2 (GPLv2)
